silver_ai/__init__.py
silver_ai/core.py
silver_ai/rules.py
silver_ai-0.1.6.dist-info/METADATA
silver_ai-0.1.6.dist-info/WHEEL
silver_ai-0.1.6.dist-info/licenses/LICENSE
silver_ai-0.1.6.dist-info/RECORD
