Metadata-Version: 2.4
Name: silver-ai
Version: 0.1.6
Summary: Deterministic state-guardrails for agentic hardware & critical systems.
License: Apache-2.0
License-File: LICENSE
Keywords: ai,agents,safety,guardrails,robotics,iot
Author: Goh Chun Lin
Author-email: chunlin@live.com.sg
Requires-Python: >=3.11,<4.0
Classifier: Development Status :: 3 - Alpha
Classifier: Framework :: Pydantic
Classifier: Intended Audience :: Developers
Classifier: License :: OSI Approved :: Apache Software License
Classifier: Programming Language :: Python :: 3
Classifier: Programming Language :: Python :: 3.11
Classifier: Programming Language :: Python :: 3.12
Classifier: Programming Language :: Python :: 3.13
Classifier: Programming Language :: Python :: 3.14
Classifier: Topic :: Scientific/Engineering :: Artificial Intelligence
Project-URL: Homepage, https://github.com/gcl-team/SilverAi
Project-URL: Repository, https://github.com/gcl-team/SilverAi
